gmailconnector/__init__.py
gmailconnector/read_email.py
gmailconnector/send_email.py
gmailconnector/send_sms.py
gmailconnector/sms_deleter.py
gmailconnector/lib/requirements.txt
gmailconnector/models/config.py
gmailconnector/models/options.py
gmailconnector/models/responder.py
gmailconnector/validator/address.py
gmailconnector/validator/domain.py
gmailconnector/validator/exceptions.py
gmailconnector/validator/validate_email.py
gmail_connector-1.0.3.dist-info/LICENSE
gmail_connector-1.0.3.dist-info/METADATA
gmail_connector-1.0.3.dist-info/WHEEL
gmail_connector-1.0.3.dist-info/top_level.txt
gmail_connector-1.0.3.dist-info/RECORD
