Metadata-Version: 2.1
Name: gmail-connector
Version: 1.0.3
Summary: Python module to, send SMS, emails and read emails
Author-email: Vignesh Rao <svignesh1793@gmail.com>
License: MIT License
Project-URL: Homepage, https://github.com/thevickypedia/gmail-connector
Project-URL: Docs, https://thevickypedia.github.io/gmail-connector/
Project-URL: Source, https://github.com/thevickypedia/gmail-connector
Project-URL: Bug Tracker, https://github.com/thevickypedia/gmail-connector/issues
Project-URL: Release Notes, https://github.com/thevickypedia/gmail-connector/blob/main/release_notes.rst
Keywords: gmail,smtp,imap,tls,ssl
Classifier: Development Status :: 5 - Production/Stable
Classifier: Intended Audience :: Telecommunications Industry
Classifier: Intended Audience :: Information Technology
Classifier: License :: OSI Approved :: MIT License
Classifier: Operating System :: OS Independent
Classifier: License :: OSI Approved :: MIT License
Classifier: Programming Language :: Python :: 3.8
Classifier: Programming Language :: Python :: 3.9
Classifier: Programming Language :: Python :: 3.10
Classifier: Programming Language :: Python :: 3.11
Classifier: Topic :: Communications :: Email
Requires-Python: >=3.8
License-File: LICENSE
Requires-Dist: dnspython==2.6.1
Requires-Dist: idna==3.*
Requires-Dist: pydantic[email]==2.*
Requires-Dist: pydantic_settings==2.*
Requires-Dist: pytz
Provides-Extra: dev
Requires-Dist: sphinx==5.1.1; extra == "dev"
Requires-Dist: pre-commit; extra == "dev"
Requires-Dist: recommonmark; extra == "dev"
Requires-Dist: gitverse; extra == "dev"
